Divider/buildingBlocks/and_gate.v
module andGate(a,b,out);
input a; 
input b; 
output out; 

assign out = a&b; 
endmodule

Divider/buildingBlocks/d_flipflopwr.v
module dFlipFlopWR(clk, rst, in, out, not_out);
    input clk;
    input in; 
    input rst; 
    output reg out; 
    output reg not_out;

    always @(posedge clk or posedge rst) begin
        if (rst == 1'b1) begin
            out <= 1'b0; 
            not_out <= 1'b1;
        end else begin
            out <= in; 
            not_out <= ~in; 
        end
    end
endmodule

Divider/phaseDetector/phaseFrequencyDetector.v
`include "../buildingBlocks/d_flipflopwr.v"
`include "../buildingBlocks/and_gate.v"

module phaseFreqDet(ref_clk, vco_clk, high1, high2, out_p, out_n);
    input ref_clk;
    input vco_clk;
    input high1; 
    input high2;
    output out_p;
    output out_n; 

    wire and_out; 
    wire dff1_out, dff1_outb;
    wire dff2_out, dff2_outb; 

    // dFlipFlopWR (clock, reset, D, Q, Qb)
    dFlipFlopWR dffwr1(ref_clk, and_out, high1, dff1_out, dff1_outb);
    dFlipFlopWR dffwr2(vco_clk, and_out, high2, dff2_out, dff2_outb);
    andGate and1(dff1_out, dff2_out, and_out); 

    // Assigning outputs
    assign out_p = dff1_out;
    assign out_n = dff2_out;

endmodule

Divider/phaseDetector/tb_pfd.v
`include "phaseFrequencyDetector.v"
`timescale 1ns/1ps

//pfd (ref_clk, vco_clk, D1, D2, Q1, Q2)
module tb_pfd(); 
reg ref_clk; 
reg vco_clk; 
reg D1, D2; 
wire Q1, Q2; 

phaseFreqDet uut(ref_clk, vco_clk, D1, D2, Q1, Q2); 

initial begin 
    D1 = 1; 
    D2 = 1;
end

initial begin
    ref_clk = 0; 
    forever #0.5 ref_clk = ~ref_clk;
end

initial begin
    #0.1
    vco_clk = 0; 
    forever #0.5 vco_clk = ~vco_clk; 
end 

initial begin 
    $dumpfile("pfd.vcd");
    $dumpvars(0, tb_pfd);
end

initial begin
    force uut.dffwr1.out = 1'b0;
    force uut.dffwr1.not_out = 1'b1;
    force uut.dffwr2.out = 1'b1;
    force uut.dffwr2.not_out = 1'b0;
    #1
    release uut.dffwr1.out;
    release uut.dffwr1.not_out;
    release uut.dffwr2.out;
    release uut.dffwr2.not_out;
end


initial #50 $finish; 





endmodule

Divider/phaseDetector/pfd.vcd
$date
	Mon Jun 10 21:48:34 2024
$end
$version
	Icarus Verilog
$end
$timescale
	1ps
$end
$scope module tb_pfd $end
$var wire 1 ! Q2 $end
$var wire 1 " Q1 $end
$var reg 1 # D1 $end
$var reg 1 $ D2 $end
$var reg 1 % ref_clk $end
$var reg 1 & vco_clk $end
$scope module uut $end
$var wire 1 # high1 $end
$var wire 1 $ high2 $end
$var wire 1 ! out_n $end
$var wire 1 " out_p $end
$var wire 1 % ref_clk $end
$var wire 1 & vco_clk $end
$var wire 1 ' dff2_outb $end
$var wire 1 ( dff2_out $end
$var wire 1 ) dff1_outb $end
$var wire 1 * dff1_out $end
$var wire 1 + and_out $end
$scope module and1 $end
$var wire 1 + out $end
$var wire 1 ( b $end
$var wire 1 * a $end
$upscope $end
$scope module dffwr1 $end
$var wire 1 % clk $end
$var wire 1 # in $end
$var wire 1 + rst $end
$var reg 1 ) not_out $end
$var reg 1 * out $end
$upscope $end
$scope module dffwr2 $end
$var wire 1 & clk $end
$var wire 1 $ in $end
$var wire 1 + rst $end
$var reg 1 ' not_out $end
$var reg 1 ( out $end
$upscope $end
$upscope $end
$upscope $end
$enddefinitions $end
$comment Show the parameter values. $end
$dumpall
$end
#0
$dumpvars
0+
0*
1)
1(
0'
x&
0%
1$
1#
0"
1!
$end
#100
0&
#500
1)
0*
1%
#600
0'
1(
1&
#1000
0%
1)
0*
#1100
0&
#1500
1'
0!
0(
0+
1)
0"
0*
1%
#1600
0'
1!
1(
1&
#2000
0%
#2100
0&
#2500
1'
0!
0(
0+
1)
0"
0*
1%
#2600
0'
1!
1(
1&
#3000
0%
#3100
0&
#3500
1'
0!
0(
0+
1)
0"
0*
1%
#3600
0'
1!
1(
1&
#4000
0%
#4100
0&
#4500
1'
0!
0(
0+
1)
0"
0*
1%
#4600
0'
1!
1(
1&
#5000
0%
#5100
0&
#5500
1'
0!
0(
0+
1)
0"
0*
1%
#5600
0'
1!
1(
1&
#6000
0%
#6100
0&
#6500
1'
0!
0(
0+
1)
0"
0*
1%
#6600
0'
1!
1(
1&
#7000
0%
#7100
0&
#7500
1'
0!
0(
0+
1)
0"
0*
1%
#7600
0'
1!
1(
1&
#8000
0%
#8100
0&
#8500
1'
0!
0(
0+
1)
0"
0*
1%
#8600
0'
1!
1(
1&
#9000
0%
#9100
0&
#9500
1'
0!
0(
0+
1)
0"
0*
1%
#9600
0'
1!
1(
1&
#10000
0%
#10100
0&
#10500
1'
0!
0(
0+
1)
0"
0*
1%
#10600
0'
1!
1(
1&
#11000
0%
#11100
0&
#11500
1'
0!
0(
0+
1)
0"
0*
1%
#11600
0'
1!
1(
1&
#12000
0%
#12100
0&
#12500
1'
0!
0(
0+
1)
0"
0*
1%
#12600
0'
1!
1(
1&
#13000
0%
#13100
0&
#13500
1'
0!
0(
0+
1)
0"
0*
1%
#13600
0'
1!
1(
1&
#14000
0%
#14100
0&
#14500
1'
0!
0(
0+
1)
0"
0*
1%
#14600
0'
1!
1(
1&
#15000
0%
#15100
0&
#15500
1'
0!
0(
0+
1)
0"
0*
1%
#15600
0'
1!
1(
1&
#16000
0%
#16100
0&
#16500
1'
0!
0(
0+
1)
0"
0*
1%
#16600
0'
1!
1(
1&
#17000
0%
#17100
0&
#17500
1'
0!
0(
0+
1)
0"
0*
1%
#17600
0'
1!
1(
1&
#18000
0%
#18100
0&
#18500
1'
0!
0(
0+
1)
0"
0*
1%
#18600
0'
1!
1(
1&
#19000
0%
#19100
0&
#19500
1'
0!
0(
0+
1)
0"
0*
1%
#19600
0'
1!
1(
1&
#20000
0%
#20100
0&
#20500
1'
0!
0(
0+
1)
0"
0*
1%
#20600
0'
1!
1(
1&
#21000
0%
#21100
0&
#21500
1'
0!
0(
0+
1)
0"
0*
1%
#21600
0'
1!
1(
1&
#22000
0%
#22100
0&
#22500
1'
0!
0(
0+
1)
0"
0*
1%
#22600
0'
1!
1(
1&
#23000
0%
#23100
0&
#23500
1'
0!
0(
0+
1)
0"
0*
1%
#23600
0'
1!
1(
1&
#24000
0%
#24100
0&
#24500
1'
0!
0(
0+
1)
0"
0*
1%
#24600
0'
1!
1(
1&
#25000
0%
#25100
0&
#25500
1'
0!
0(
0+
1)
0"
0*
1%
#25600
0'
1!
1(
1&
#26000
0%
#26100
0&
#26500
1'
0!
0(
0+
1)
0"
0*
1%
#26600
0'
1!
1(
1&
#27000
0%
#27100
0&
#27500
1'
0!
0(
0+
1)
0"
0*
1%
#27600
0'
1!
1(
1&
#28000
0%
#28100
0&
#28500
1'
0!
0(
0+
1)
0"
0*
1%
#28600
0'
1!
1(
1&
#29000
0%
#29100
0&
#29500
1'
0!
0(
0+
1)
0"
0*
1%
#29600
0'
1!
1(
1&
#30000
0%
#30100
0&
#30500
1'
0!
0(
0+
1)
0"
0*
1%
#30600
0'
1!
1(
1&
#31000
0%
#31100
0&
#31500
1'
0!
0(
0+
1)
0"
0*
1%
#31600
0'
1!
1(
1&
#32000
0%
#32100
0&
#32500
1'
0!
0(
0+
1)
0"
0*
1%
#32600
0'
1!
1(
1&
#33000
0%
#33100
0&
#33500
1'
0!
0(
0+
1)
0"
0*
1%
#33600
0'
1!
1(
1&
#34000
0%
#34100
0&
#34500
1'
0!
0(
0+
1)
0"
0*
1%
#34600
0'
1!
1(
1&
#35000
0%
#35100
0&
#35500
1'
0!
0(
0+
1)
0"
0*
1%
#35600
0'
1!
1(
1&
#36000
0%
#36100
0&
#36500
1'
0!
0(
0+
1)
0"
0*
1%
#36600
0'
1!
1(
1&
#37000
0%
#37100
0&
#37500
1'
0!
0(
0+
1)
0"
0*
1%
#37600
0'
1!
1(
1&
#38000
0%
#38100
0&
#38500
1'
0!
0(
0+
1)
0"
0*
1%
#38600
0'
1!
1(
1&
#39000
0%
#39100
0&
#39500
1'
0!
0(
0+
1)
0"
0*
1%
#39600
0'
1!
1(
1&
#40000
0%
#40100
0&
#40500
1'
0!
0(
0+
1)
0"
0*
1%
#40600
0'
1!
1(
1&
#41000
0%
#41100
0&
#41500
1'
0!
0(
0+
1)
0"
0*
1%
#41600
0'
1!
1(
1&
#42000
0%
#42100
0&
#42500
1'
0!
0(
0+
1)
0"
0*
1%
#42600
0'
1!
1(
1&
#43000
0%
#43100
0&
#43500
1'
0!
0(
0+
1)
0"
0*
1%
#43600
0'
1!
1(
1&
#44000
0%
#44100
0&
#44500
1'
0!
0(
0+
1)
0"
0*
1%
#44600
0'
1!
1(
1&
#45000
0%
#45100
0&
#45500
1'
0!
0(
0+
1)
0"
0*
1%
#45600
0'
1!
1(
1&
#46000
0%
#46100
0&
#46500
1'
0!
0(
0+
1)
0"
0*
1%
#46600
0'
1!
1(
1&
#47000
0%
#47100
0&
#47500
1'
0!
0(
0+
1)
0"
0*
1%
#47600
0'
1!
1(
1&
#48000
0%
#48100
0&
#48500
1'
0!
0(
0+
1)
0"
0*
1%
#48600
0'
1!
1(
1&
#49000
0%
#49100
0&
#49500
1'
0!
0(
0+
1)
0"
0*
1%
#49600
0'
1!
1(
1&
