Divider/buildingBlocks/d_flipflop.v
module dFlipFlop(clk,in,out,not_out);
input clk;
input in; 
output reg out; 
output reg not_out;

always @(posedge clk) begin
    out <= in; 
    not_out <= ~in; 
end
endmodule

Divider/buildingBlocks/and_gate.v
module andGate(a,b,out);
input a; 
input b; 
output out; 

assign out = a&b; 
endmodule

Divider/buildingBlocks/or_gate.v
module orGate(a,b,out);
input a;
input b;
output out; 

assign out = a|b; 
endmodule

Divider/divBy3or4/divBy3or4.v
`include "../buildingBlocks/dFlipFlop.v"
`include "../buildingBlocks/andGate.v"
`include "../buildingBlocks/orGate.v" 

module divBy3or4(clk_in,mod,clk_out);
input clk_in;
input mod; 
output clk_out; 

wire or_out;
wire and_out; 
wire dff1_out, dff1_outb; 
wire dff2_out; 

//dff (clk, D, Q, Qb)
//and (in1, in2, out)
//or (in1, in2, out)
dFlipFlop dff1(clk_in,clk_out,dff1_out,dff1_outb);
orGate or1(clk_out,mod,or_out); 
andGate and1(or_out,dff1_out,and_out); 
dFlipFlop dff2(clk_in,and_out,dff2_out,clk_out);
endmodule

Divider/divBy3or4/tb_div3or4.v
`include "divBy3or4.v"
`timescale 1ns/1ps 

module tb_div3or4();
reg clk_in; 
reg mod; 
wire clk_out; 

divBy3or4 uut(clk_in,mod,clk_out); 

initial begin
    clk_in = 0; 
    forever #0.5 clk_in = ~clk_in;        
end

initial begin
    mod = 1; 
    #15 mod = 0; 
    #15 mod = 1; 
end

initial begin
    $dumpfile("divBy3or4.vcd");
    $dumpvars(0, tb_div3or4);
end

initial begin
    force uut.dff1.out = 1'b0;
    force uut.dff1.not_out = 1'b1;
    force uut.dff2.out = 1'b1;
    force uut.dff2.not_out = 1'b0;
    #1 
    release uut.dff1.out;
    release uut.dff1.not_out;
    release uut.dff2.out;
    release uut.dff2.not_out;
end

initial #50 $finish; 

endmodule

Divider/divBy3or4/divBy3or4.vcd
$date
	Tue Jun 11 17:28:00 2024
$end
$version
	Icarus Verilog
$end
$timescale
	1ps
$end
$scope module tb_div3or4 $end
$var wire 1 ! clk_out $end
$var reg 1 " clk_in $end
$var reg 1 # mod $end
$scope module uut $end
$var wire 1 " clk_in $end
$var wire 1 # mod $end
$var wire 1 $ or_out $end
$var wire 1 % dff2_out $end
$var wire 1 & dff1_outb $end
$var wire 1 ' dff1_out $end
$var wire 1 ! clk_out $end
$var wire 1 ( and_out $end
$scope module and1 $end
$var wire 1 ( out $end
$var wire 1 ' b $end
$var wire 1 $ a $end
$upscope $end
$scope module dff1 $end
$var wire 1 " clk $end
$var wire 1 ! in $end
$var reg 1 & not_out $end
$var reg 1 ' out $end
$upscope $end
$scope module dff2 $end
$var wire 1 " clk $end
$var wire 1 ( in $end
$var reg 1 ! not_out $end
$var reg 1 % out $end
$upscope $end
$scope module or1 $end
$var wire 1 ! a $end
$var wire 1 # b $end
$var wire 1 $ out $end
$upscope $end
$upscope $end
$upscope $end
$enddefinitions $end
$comment Show the parameter values. $end
$dumpall
$end
#0
$dumpvars
0(
0'
1&
1%
1$
1#
0"
0!
$end
#500
1&
0'
0!
1%
1"
#1000
0"
0!
1%
#1500
1!
0%
1"
#2000
0"
#2500
1(
0&
1'
1"
#3000
0"
#3500
0!
1%
1"
#4000
0"
#4500
0(
1&
0'
1"
#5000
0"
#5500
1!
0%
1"
#6000
0"
#6500
1(
0&
1'
1"
#7000
0"
#7500
0!
1%
1"
#8000
0"
#8500
0(
1&
0'
1"
#9000
0"
#9500
1!
0%
1"
#10000
0"
#10500
1(
0&
1'
1"
#11000
0"
#11500
0!
1%
1"
#12000
0"
#12500
0(
1&
0'
1"
#13000
0"
#13500
1!
0%
1"
#14000
0"
#14500
1(
0&
1'
1"
#15000
0"
0#
#15500
0(
0$
0!
1%
1"
#16000
0"
#16500
1$
1&
0'
1!
0%
1"
#17000
0"
#17500
1(
0&
1'
1"
#18000
0"
#18500
0(
0$
0!
1%
1"
#19000
0"
#19500
1$
1!
0%
1&
0'
1"
#20000
0"
#20500
1(
0&
1'
1"
#21000
0"
#21500
0(
0$
0!
1%
1"
#22000
0"
#22500
1$
1&
0'
1!
0%
1"
#23000
0"
#23500
1(
0&
1'
1"
#24000
0"
#24500
0(
0$
0!
1%
1"
#25000
0"
#25500
1$
1!
0%
1&
0'
1"
#26000
0"
#26500
1(
0&
1'
1"
#27000
0"
#27500
0(
0$
0!
1%
1"
#28000
0"
#28500
1$
1&
0'
1!
0%
1"
#29000
0"
#29500
1(
0&
1'
1"
#30000
0"
1#
#30500
0!
1%
1"
#31000
0"
#31500
0(
1&
0'
1"
#32000
0"
#32500
1!
0%
1"
#33000
0"
#33500
1(
0&
1'
1"
#34000
0"
#34500
0!
1%
1"
#35000
0"
#35500
0(
1&
0'
1"
#36000
0"
#36500
1!
0%
1"
#37000
0"
#37500
1(
0&
1'
1"
#38000
0"
#38500
0!
1%
1"
#39000
0"
#39500
0(
1&
0'
1"
#40000
0"
#40500
1!
0%
1"
#41000
0"
#41500
1(
0&
1'
1"
#42000
0"
#42500
0!
1%
1"
#43000
0"
#43500
0(
1&
0'
1"
#44000
0"
#44500
1!
0%
1"
#45000
0"
#45500
1(
0&
1'
1"
#46000
0"
#46500
0!
1%
1"
#47000
0"
#47500
0(
1&
0'
1"
#48000
0"
#48500
1!
0%
1"
#49000
0"
#49500
1(
0&
1'
1"
