3b-mux_dec/dec_3x8.v
module dec_3x8(not_y,y,in,en);
    input [2:0] in;
    input en;  
    output reg [7:0]y;
    output reg [7:0]not_y; 

    always @(in,en)
        begin
            if (en==0)
            begin
                if(in[2]==1'b0 & in[1]==1'b0 & in[0]==1'b0)
                    y=8'b11111110;
                else if(in[2]==1'b0 & in[1]==1'b0 & in[0]==1'b1)
                    y=8'b11111101;      
                else if(in[2]==1'b0 & in[1]==1'b1 & in[0]==1'b0)
                    y=8'b11111011;
                else if(in[2]==1'b0 & in[1]==1'b1 & in[0]==1'b1)
                    y=8'b11110111; 
                else if(in[2]==1'b1 & in[1]==1'b0 & in[0]==1'b0)
                    y=8'b11101111;
                else if(in[2]==1'b1 & in[1]==1'b0 & in[0]==1'b1)
                    y=8'b11011111;      
                else if(in[2]==1'b1 & in[1]==1'b1 & in[0]==1'b0)
                    y=8'b10111111;
                else if(in[2]==1'b1 & in[1]==1'b1 & in[0]==1'b1)
                    y=8'b01111111;      
                else 
                    y=8'bxxxxxxxx;   
                not_y = ~y;
            end
            else 
                y=8'b11111111;
        end
endmodule

3x8_decoder/test_dec_3x8.v
module test_dec_3x8;
    reg [2:0] in; 
    reg en; 
    wire [7:0]y; 
    wire [7:0]not_y;

    dec_3x8 dut(not_y,y,in,en);

    initial begin 
        $dumpfile("test.vcd");
        $dumpvars(0,test_dec_3x8); 

        en=1'b1; in[2]=1'bx; in[1]=1'bx; in[0]=1'bx; #5 
        en=1'b0; in[2]=1'b0; in[1]=1'b0; in[0]=1'b0; #5 
        en=1'b0; in[2]=1'b0; in[1]=1'b0; in[0]=1'b1; #5   
        en=1'b0; in[2]=1'b0; in[1]=1'b1; in[0]=1'b0; #5    
        en=1'b0; in[2]=1'b0; in[1]=1'b1; in[0]=1'b1; #5
        en=1'b0; in[2]=1'b1; in[1]=1'b0; in[0]=1'b0; #5 
        en=1'b0; in[2]=1'b1; in[1]=1'b0; in[0]=1'b1; #5   
        en=1'b0; in[2]=1'b1; in[1]=1'b1; in[0]=1'b0; #5    
        en=1'b0; in[2]=1'b1; in[1]=1'b1; in[0]=1'b1;     
    end

    initial #45 $finish; 
endmodule

3x8_decoder/test.vcd
$date
	Mon Aug 28 20:16:48 2023
$end
$version
	Icarus Verilog
$end
$timescale
	1s
$end
$scope module test_dec_3x8 $end
$var wire 8 ! y [7:0] $end
$var wire 8 " not_y [7:0] $end
$var reg 1 # en $end
$var reg 3 $ in [2:0] $end
$scope module dut $end
$var wire 1 # en $end
$var wire 3 % in [2:0] $end
$var reg 8 & not_y [7:0] $end
$var reg 8 ' y [7:0] $end
$upscope $end
$upscope $end
$enddefinitions $end
#0
$dumpvars
b11111111 '
bx &
bx %
bx $
1#
bx "
b11111111 !
$end
#5
b1 "
b1 &
b11111110 !
b11111110 '
b0 $
b0 %
0#
#10
b10 "
b10 &
b11111101 !
b11111101 '
b1 $
b1 %
#15
b100 "
b100 &
b11111011 !
b11111011 '
b10 $
b10 %
#20
b1000 "
b1000 &
b11110111 !
b11110111 '
b11 $
b11 %
#25
b10000 "
b10000 &
b11101111 !
b11101111 '
b100 $
b100 %
#30
b100000 "
b100000 &
b11011111 !
b11011111 '
b101 $
b101 %
#35
b1000000 "
b1000000 &
b10111111 !
b10111111 '
b110 $
b110 %
#40
b10000000 "
b10000000 &
b1111111 !
b1111111 '
b111 $
b111 %
