Divider/buildingBlocks/or_gate.v
module orGate(a,b,out);
input a;
input b;
output out; 

assign out = a|b; 
endmodule

Divider/buildingBlocks/d_flipflop.v
module dFlipFlop(clk,in,out,not_out);
input clk;
input in; 
output reg out; 
output reg not_out;

always @(posedge clk) begin
    out <= in; 
    not_out <= ~in; 
end
endmodule

Divider/buildingBlocks/and_gate.v
module andGate(a,b,out);
input a; 
input b; 
output out; 

assign out = a&b; 
endmodule

Divider/divBy2or3/div2or3.v
`include "../buildingBlocks/d_flipflop.v"
`include "../buildingBlocks/and_gate.v"
`include "../buildingBlocks/or_gate.v" 

module divBy2or3(clk_in, mod, Qb); 
input clk_in; 
input mod; 
output Qb; 

wire and1_out;
wire and2_out;
wire dff1_out,dff1_outb; 
wire dff2_out;

andGate and1(dff2_out,mod,and1_out);
dFlipFlop dff1(clk_in,and1_out,dff1_out,dff1_outb);
andGate and2(Qb,dff1_outb,and2_out); 
dFlipFlop dff2(clk_in,and2_out,dff2_out,Qb);
endmodule

Divider/divBy2or3/tb_div2or3.v
`include "div2or3.v"
`timescale 1ns/1ps 

module tb_div2or3();
reg clk_in; 
reg mod; 
wire clk_out_proper;
wire clk_out; 

divBy2or3 uut(clk_in,mod,clk_out); 

initial begin
    clk_in = 0; 
    forever #0.5 clk_in = ~clk_in;        
end

initial begin
    mod = 1; 
    #15 mod = 0; 
    #15 mod = 1; 
end

initial begin
    $dumpfile("divBy2or3.vcd");
    $dumpvars(0, tb_div2or3);
end

initial begin
    force uut.dff1.out = 1'b1;
    force uut.dff1.not_out = 1'b0;
    force uut.dff2.out = 1'b1;
    force uut.dff2.not_out = 1'b0;
    #1 
    release uut.dff1.out;
    release uut.dff1.not_out;
    release uut.dff2.out;
    release uut.dff2.not_out;
end

initial #50 $finish; 

endmodule

Divider/divBy2or3/divBy2or3.vcd
$date
	Mon Jun 10 17:14:06 2024
$end
$version
	Icarus Verilog
$end
$timescale
	1ps
$end
$scope module tb_div2or3 $end
$var wire 1 ! clk_out $end
$var reg 1 " clk_in $end
$var reg 1 # mod $end
$scope module uut $end
$var wire 1 " clk_in $end
$var wire 1 # mod $end
$var wire 1 $ dff2_out $end
$var wire 1 % dff1_outb $end
$var wire 1 & dff1_out $end
$var wire 1 ' and2_out $end
$var wire 1 ( and1_out $end
$var wire 1 ! Qb $end
$scope module and1 $end
$var wire 1 # b $end
$var wire 1 ( out $end
$var wire 1 $ a $end
$upscope $end
$scope module and2 $end
$var wire 1 ' out $end
$var wire 1 % b $end
$var wire 1 ! a $end
$upscope $end
$scope module dff1 $end
$var wire 1 " clk $end
$var wire 1 ( in $end
$var reg 1 % not_out $end
$var reg 1 & out $end
$upscope $end
$scope module dff2 $end
$var wire 1 " clk $end
$var wire 1 ' in $end
$var reg 1 ! not_out $end
$var reg 1 $ out $end
$upscope $end
$upscope $end
$upscope $end
$enddefinitions $end
$comment Show the parameter values. $end
$dumpall
$end
#0
$dumpvars
1(
0'
1&
0%
1$
1#
0"
0!
$end
#500
0%
1&
0!
1$
1"
#1000
0"
0!
1$
#1500
0(
1!
0$
1"
#2000
0"
#2500
1'
1%
0&
1"
#3000
0"
#3500
0'
1(
0!
1$
1"
#4000
0"
#4500
0(
0%
1&
1!
0$
1"
#5000
0"
#5500
1'
1%
0&
1"
#6000
0"
#6500
0'
1(
0!
1$
1"
#7000
0"
#7500
0(
1!
0$
0%
1&
1"
#8000
0"
#8500
1'
1%
0&
1"
#9000
0"
#9500
0'
1(
0!
1$
1"
#10000
0"
#10500
0(
0%
1&
1!
0$
1"
#11000
0"
#11500
1'
1%
0&
1"
#12000
0"
#12500
0'
1(
0!
1$
1"
#13000
0"
#13500
0(
1!
0$
0%
1&
1"
#14000
0"
#14500
1'
1%
0&
1"
#15000
0"
0#
#15500
0'
0!
1$
1"
#16000
0"
#16500
1'
1!
0$
1"
#17000
0"
#17500
0'
0!
1$
1"
#18000
0"
#18500
1'
1!
0$
1"
#19000
0"
#19500
0'
0!
1$
1"
#20000
0"
#20500
1'
1!
0$
1"
#21000
0"
#21500
0'
0!
1$
1"
#22000
0"
#22500
1'
1!
0$
1"
#23000
0"
#23500
0'
0!
1$
1"
#24000
0"
#24500
1'
1!
0$
1"
#25000
0"
#25500
0'
0!
1$
1"
#26000
0"
#26500
1'
1!
0$
1"
#27000
0"
#27500
0'
0!
1$
1"
#28000
0"
#28500
1'
1!
0$
1"
#29000
0"
#29500
0'
0!
1$
1"
#30000
1(
0"
1#
#30500
0(
0%
1&
1!
0$
1"
#31000
0"
#31500
1'
1%
0&
1"
#32000
0"
#32500
0'
1(
0!
1$
1"
#33000
0"
#33500
0(
1!
0$
0%
1&
1"
#34000
0"
#34500
1'
1%
0&
1"
#35000
0"
#35500
0'
1(
0!
1$
1"
#36000
0"
#36500
0(
0%
1&
1!
0$
1"
#37000
0"
#37500
1'
1%
0&
1"
#38000
0"
#38500
0'
1(
0!
1$
1"
#39000
0"
#39500
0(
1!
0$
0%
1&
1"
#40000
0"
#40500
1'
1%
0&
1"
#41000
0"
#41500
0'
1(
0!
1$
1"
#42000
0"
#42500
0(
0%
1&
1!
0$
1"
#43000
0"
#43500
1'
1%
0&
1"
#44000
0"
#44500
0'
1(
0!
1$
1"
#45000
0"
#45500
0(
1!
0$
0%
1&
1"
#46000
0"
#46500
1'
1%
0&
1"
#47000
0"
#47500
0'
1(
0!
1$
1"
#48000
0"
#48500
0(
0%
1&
1!
0$
1"
#49000
0"
#49500
1'
1%
0&
1"
